{
  "name": "logos/X1vtFPS7foL6L9ZwAEm7RYQ9hkKe.png",
  "bucket": "xscan-9120f.appspot.com",
  "metageneration": 1,
  "generation": 1687617989494,
  "contentType": "image/png",
  "storageClass": "STANDARD",
  "contentDisposition": "inline",
  "downloadTokens": [
    "0635904f-e00e-403d-8016-f5be900db3da"
  ],
  "etag": "bWSVAnw3UG0AVxY+fMBaoeIcdYw",
  "customMetadata": {},
  "timeCreated": "2023-06-24T14:46:29.494Z",
  "updated": "2023-06-24T14:46:29.494Z",
  "size": 57224,
  "md5Hash": "xMIfIwg3lEqF/bir+TAQ6Q==",
  "crc32c": "4189586587"
}